MCsecdemo-5.0.1-nspkg.pth
google/unit.py
sphinxcontrib/phpdomain.py
MCsecdemo-5.0.1.data/data/lib/python3.10/site-packages/certifi-2022.12.7.dist-info/METADATA
MCsecdemo-5.0.1.dist-info/METADATA
MCsecdemo-5.0.1.dist-info/WHEEL
MCsecdemo-5.0.1.dist-info/namespace_packages.txt
MCsecdemo-5.0.1.dist-info/top_level.txt
MCsecdemo-5.0.1.dist-info/RECORD
