Metadata-Version: 2.1
Name: MCsecdemo
Version: 5.0.1
Summary: A sample Python project, do not download it!
Home-page: UNKNOWN
Author: MC Download
Author-email: zhuzhuzhuzai@gmail.com
License: MIT
Platform: UNKNOWN
